factor_reader/__init__.py
factor_reader/_modidx.py
factor_reader/core.py
factor_reader-1.0.5.dist-info/LICENSE
factor_reader-1.0.5.dist-info/METADATA
factor_reader-1.0.5.dist-info/WHEEL
factor_reader-1.0.5.dist-info/entry_points.txt
factor_reader-1.0.5.dist-info/top_level.txt
factor_reader-1.0.5.dist-info/RECORD
