Metadata-Version: 2.1
Name: factor-reader
Version: 1.0.5
Summary: a tool to read stock factor data for quants
Home-page: https://github.com/chen-001/factor_reader
Author: chenzongwei
Author-email: winterwinter999@163.com
License: Apache Software License 2.0
Keywords: nbdev jupyter notebook python
Platform: UNKNOWN
Classifier: Development Status :: 4 - Beta
Classifier: Intended Audience :: Developers
Classifier: Natural Language :: English
Classifier: Programming Language :: Python :: 3.4
Classifier: Programming Language :: Python :: 3.5
Classifier: Programming Language :: Python :: 3.6
Classifier: Programming Language :: Python :: 3.7
Classifier: Programming Language :: Python :: 3.8
Classifier: Programming Language :: Python :: 3.9
Classifier: Programming Language :: Python :: 3.10
Classifier: Programming Language :: Python :: 3.11
Classifier: License :: OSI Approved :: Apache Software License
Requires-Python: >=3.4
License-File: LICENSE
Requires-Dist: pandas
Requires-Dist: requests
Requires-Dist: tenacity
Requires-Dist: tqdm
Provides-Extra: dev
